pylink/__version__.py
pylink/pylink_cg.cp312-win_amd64.pyd
pylink/eyelink_core64.dll
pylink/eyelink_core_graphics64.dll
pylink/__init__.py
pylink/eyelink.py
pylink/pylink_c.cp312-win_amd64.pyd
pylink/constants.py
pylink/tracker.py
sr_research_pylink-2.1.1145.post1.dist-info/top_level.txt
sr_research_pylink-2.1.1145.post1.dist-info/METADATA
sr_research_pylink-2.1.1145.post1.dist-info/WHEEL
sr_research_pylink-2.1.1145.post1.dist-info/RECORD
