Metadata-Version: 2.1
Name: sr-research-pylink
Version: 2.1.1145.post1
Summary: Python module for interfacing SR Research EyeLink eye trackers
Home-page: https://www.sr-research.com/support
Author: SR Research Ltd
Author-email: support@sr-research.com
License: SR Research Ltd 
Classifier: Operating System :: POSIX :: Linux
Classifier: Development Status :: 5 - Production/Stable
Classifier: Programming Language :: Python
Classifier: Programming Language :: Python :: 3.12
Classifier: Intended Audience :: Science/Research
Classifier: Intended Audience :: Developers
Classifier: Intended Audience :: End Users/Desktop
Classifier: Topic :: Scientific/Engineering
Classifier: Topic :: Scientific/Engineering :: Interface Engine/Protocol Translator
Classifier: Topic :: Software Development :: Libraries :: Python Modules
Classifier: License :: Free For Educational Use
Classifier: License :: Free for non-commercial use
Classifier: License :: Other/Proprietary License
